docs/__init__.py
docs/conf.py
privapy/__init__.py
privapy/module.py
privapy/image/__init__.py
privapy/image/cleaner.py
privapy/image/methods/__init__.py
privapy/image/methods/base.py
privapy/image/methods/cleaner/__init__.py
privapy/image/methods/cleaner/blur.py
privapy/image/methods/model/__init__.py
privapy/image/methods/model/huggingface.py
privapy/text/__init__.py
privapy/text/cleaner.py
privapy/text/methods/__init__.py
privapy/text/methods/base.py
privapy/text/methods/model/__init__.py
privapy/text/methods/model/huggingface.py
privapy/text/methods/regex/__init__.py
privapy/text/methods/regex/date.py
privapy/text/methods/regex/email.py
privapy/text/methods/regex/time.py
tests/__init__.py
tests/test_example.py
privapy-0.0.4.dist-info/LICENSE.txt
privapy-0.0.4.dist-info/METADATA
privapy-0.0.4.dist-info/WHEEL
privapy-0.0.4.dist-info/top_level.txt
privapy-0.0.4.dist-info/RECORD
