Metadata-Version: 2.1
Name: privapy
Version: 0.0.4
Summary: Anonymize your data
Home-page: https://github.com/vincentmin/privapy
Author: Vincent Min
License: MIT License
Keywords: anonymize
Platform: UNKNOWN
Classifier: Development Status :: 2 - Pre-Alpha
Classifier: Intended Audience :: Developers
Classifier: Topic :: Software Development :: Libraries :: Python Modules
Classifier: License :: OSI Approved :: MIT License
Classifier: Programming Language :: Python :: 3.9
Requires-Dist: transformers (==4.31.0)
Requires-Dist: torch (==2.0.1)
Requires-Dist: opencv-python (==4.8.0.76)
Requires-Dist: pillow
Requires-Dist: timm
